DataAccess/Neo4jOpr.py
DataAccess/__init__.py
Domain/Controller.py
Domain/Extractor.py
Domain/QueryBuilder.py
Domain/Repository.py
Domain/__init__.py
Presentation/Gate.py
Presentation/__init__.py
Presentation/main.py
Presentation/pres.py
generate_cypher_queries-0.1.0.dist-info/METADATA
generate_cypher_queries-0.1.0.dist-info/WHEEL
generate_cypher_queries-0.1.0.dist-info/top_level.txt
generate_cypher_queries-0.1.0.dist-info/RECORD
