Metadata-Version: 2.1
Name: generate_cypher_queries
Version: 0.1.0
Summary: Python Library for Database Interaction with Neo4j
Author: Yaki Naftali
Author-email: yaki.naftali@accenture.com
Requires-Dist: neo4j>=4.4.0
